reelay/dense_timed_monitor.py
reelay/__init__.py
reelay/discrete_timed_monitor.py
reelay/library.cpython-38-x86_64-linux-gnu.so
reelay-2008.0.dist-info/RECORD
reelay-2008.0.dist-info/LICENSE
reelay-2008.0.dist-info/top_level.txt
reelay-2008.0.dist-info/METADATA
reelay-2008.0.dist-info/WHEEL
