Metadata-Version: 1.2
Name: reelay
Version: 2008.0
Summary: Runtime verification package using formal specifications
Home-page: http://github.com/doganulus/reelay
Author: Dogan Ulus
Author-email: doganulus@gmail.com
License: MPL-2.0
Platform: UNKNOWN
Classifier: Development Status :: 4 - Beta
Classifier: Intended Audience :: Developers
Classifier: Intended Audience :: Science/Research
Classifier: Topic :: Scientific/Engineering
Classifier: Topic :: Scientific/Engineering :: Mathematics
Classifier: Topic :: Software Development :: Testing
Classifier: License :: OSI Approved :: Mozilla Public License 2.0 (MPL 2.0)
Classifier: Programming Language :: Python :: 3
Requires-Python: >=3
